{
  "BATTERY_DATA_VARS": 21,
  "BATTERY_STATE_VARS": 6,
  
  "fx_addr_separator": 10000,
  
  "float_mode": "SCALE",
  "word_order": ">",
  "byte_order": ">",
  "scaling_factor": 100,
  
  "soc": 31000,
  "active_power_in": 31002,
  "reactive_power_in" : 31004,
  "current_I1_in" : 31006,
  "current_I2_in" : 31008,
  "current_I3_in" : 31010,
  "voltage_I1_I2_in" : 31012,
  "voltage_I2_I3_in" : 31014,
  "voltage_I3_I1_in" : 31016,
  "frequency_in" : 31018,
  "active_power_out" : 31020,
  "reactive_power_out" : 31022,
  "current_I1_out" : 31024,
  "current_I2_out" : 31026,
  "current_I3_out" : 31028,
  "voltage_I1_I2_out" : 31030,
  "voltage_I2_I3_out" : 31032,
  "voltage_I3_I1_out" : 31034,
  "frequency_out" : 31036,
  "active_power_converter" : 31038,
  "reactive_power_converter" : 31040,


  "system_status" : 31042,
  "system_mode" : 31044,
  "accept_values" : 11000,
  "converter_started" : 11001,
  "input_connected" : 11002,
  "system_on_backup_battery" : 11003
}